fileservice/__init__.cpython-310-x86_64-linux-gnu.so
fileservice/fileServiceProcess.cpython-310-x86_64-linux-gnu.so
fileservice/hdf5.cpython-310-x86_64-linux-gnu.so
fileservice/backend/HDF5Service.cpython-310-x86_64-linux-gnu.so
fileservice/backend/__init__.cpython-310-x86_64-linux-gnu.so
fileservice-0.0.2.2024.9.28.23.18.dist-info/METADATA
fileservice-0.0.2.2024.9.28.23.18.dist-info/WHEEL
fileservice-0.0.2.2024.9.28.23.18.dist-info/entry_points.txt
fileservice-0.0.2.2024.9.28.23.18.dist-info/top_level.txt
fileservice-0.0.2.2024.9.28.23.18.dist-info/RECORD
