Metadata-Version: 2.1
Name: fileservice
Version: 0.0.2.2024.9.28.23.18
Summary: HDF5 and Posix remote file service
Author: zhangchenglong
Author-email: zhangchl@ihep.ac.cn
License: Mozilla Public License 2.0
Requires-Python: >=3.0
Requires-Dist: h5py
Requires-Dist: zmq
Requires-Dist: flatten-json
